pyrails/__init__.py
pyrails/main.py
pyrails/options.py
pyrails/templates/__init__.py
pyrails/templates/engine_template.py
pyrails/templates/settings_template.py
pyrails/utils/__init__.py
pyrails-0.1.1.dist-info/METADATA
pyrails-0.1.1.dist-info/WHEEL
pyrails-0.1.1.dist-info/entry_points.txt
pyrails-0.1.1.dist-info/RECORD
