Metadata-Version: 2.1
Name: pyrails
Version: 0.1.1
Summary: 
Author: Augusto2803
Author-email: augustobauerdomingos@gmail.com
Requires-Python: >=3.12,<4.0
Classifier: Programming Language :: Python :: 3
Classifier: Programming Language :: Python :: 3.12
Classifier: Programming Language :: Python :: 3.13
Requires-Dist: inquirerpy (>=0.3.4,<0.4.0)
Requires-Dist: typer (>=0.15.1,<0.16.0)
